{"cameraMode":{"drawMode":0,"name":"Shaded","section":"Shading Mode"},"sceneLighting":false,"audioPlay":false,"sceneViewState":{"showFog":true,"showMaterialUpdate":false,"showSkybox":false,"showFlares":true,"showImageEffects":true,"showParticleSystems":true},"in2DMode":false,"pivot":{"x":-0.0955190658569336,"y":-0.09157335758209229,"z":-0.24290157854557038},"rotation":{"x":-0.1338869333267212,"y":0.714747428894043,"z":-0.14251480996608735,"w":-0.6714849472045898},"size":3.6179652214050295,"orthographic":false}